{"id":"cases","slug":"cases","nameEn":"International Conference on Compilers, Architecture, and Synthesis for Embedded Systems","nameKr":null,"acronym":"CASES","field":"Architecture","subField":"Embedded Systems","dblpKey":"conf/cases","websiteUrl":"https://esweek.org/cases/","description":null,"descriptionEn":"CASES (International Conference on Compilers, Architecture, and Synthesis for Embedded Systems). Paper deadline: 2026-03-30. 2026-10-04, Barcelona, Spain. BK21 2, KIISE 우수, KAIST 우수, POSTECH 우수, CCF C. 2 best paper awards.","descriptionKo":"CASES (International Conference on Compilers, Architecture, and Synthesis for Embedded Systems). 논문 마감: 2026-03-30. 2026-10-04, Barcelona, Spain. BK21 2, KIISE 우수, KAIST 우수, POSTECH 우수, CCF C. Best Paper 2편.","nextDeadline":"2026-03-30T23:59:00Z","daysUntilDeadline":-15,"deadlineTimezone":"AoE","venue":"Barcelona, Spain","conferenceStart":"2026-10-04","conferenceEnd":"2026-10-09","institutionRatings":[{"institution":"BK21","tier":"2"},{"institution":"KIISE","tier":"우수"},{"institution":"KAIST","tier":"우수"},{"institution":"SNU","tier":null},{"institution":"POSTECH","tier":"우수"},{"institution":"CORE","tier":null},{"institution":"CCF","tier":"C"},{"institution":"CSRankings","tier":null}],"deadlines":[{"year":2026,"cycle":"main","abstractDeadline":"2026-03-23T23:59:00Z","paperDeadline":"2026-03-30T23:59:00Z","notificationDate":null,"conferenceStart":"2026-10-04","conferenceEnd":"2026-10-09","venue":"Barcelona, Spain","timezone":"AoE"}],"bestPapers":[{"year":2024,"paperTitle":"A Dataflow-aware Network-on-Interposer for CNN Inferencing in the Presence of Defective Chiplets","authors":"Sharma, Ogras, Kalyanraman & Pande","awardType":"best_paper","tags":["CNN Inference","Chiplet"],"paperUrl":"https://doi.org/10.1109/TCAD.2024.3447210"},{"year":2025,"paperTitle":"Large or Small: Harnessing the Erase Duality of Emerging Bit-Alterable NAND Flash to Suppress Tail Latency","authors":"Yao, Yang, Wang, Chen & Yang","awardType":"best_paper","tags":["NAND Flash","Storage"],"paperUrl":"https://doi.org/10.1145/3762154"}],"acceptanceRates":[],"keywordTrends":[]}