{"id":"date","slug":"date","nameEn":"Design, Automation and Test in Europe Conference","nameKr":null,"acronym":"DATE","field":"Architecture","subField":"Design Automation","dblpKey":"conf/date","websiteUrl":null,"description":null,"descriptionEn":"DATE (Design, Automation and Test in Europe Conference). Paper deadline: 2025-09-14. 2026-04-20, Verona, Italy. BK21 2, KIISE 우수, POSTECH 우수, CORE B, CCF B, KAIST 우수. 2 best paper awards.","descriptionKo":"DATE (Design, Automation and Test in Europe Conference). 논문 마감: 2025-09-14. 2026-04-20, Verona, Italy. BK21 2, KIISE 우수, POSTECH 우수, CORE B, CCF B, KAIST 우수. Best Paper 2편.","nextDeadline":"2025-09-14T23:59:00Z","daysUntilDeadline":-212,"deadlineTimezone":"AoE","venue":"Verona, Italy","conferenceStart":"2026-04-20","conferenceEnd":"2026-04-22","institutionRatings":[{"institution":"BK21","tier":"2"},{"institution":"KIISE","tier":"우수"},{"institution":"POSTECH","tier":"우수"},{"institution":"CORE","tier":"B"},{"institution":"CCF","tier":"B"},{"institution":"CSRankings","tier":null},{"institution":"KAIST","tier":"우수"},{"institution":"SNU","tier":null}],"deadlines":[{"year":2026,"cycle":"main","abstractDeadline":"2025-09-07T23:59:00Z","paperDeadline":"2025-09-14T23:59:00Z","notificationDate":null,"conferenceStart":"2026-04-20","conferenceEnd":"2026-04-22","venue":"Verona, Italy","timezone":"AoE"}],"bestPapers":[{"year":2024,"paperTitle":"FusionArch: A Fusion-Based Accelerator for Point-Based Point Cloud Neural Networks","authors":"Liu, Song, Dai, Li, Xiao, Xiang, Kong, Xu & Liang","awardType":"best_paper","tags":["Point Cloud","Accelerator"],"paperUrl":"https://doi.org/10.23919/DATE58400.2024.10546759"},{"year":2025,"paperTitle":"Timing Driven Global Placement by Efficient Critical Path Extraction","authors":"Shi, Xu, Kai, Lin, Xue, Yuan & Qian","awardType":"best_paper","tags":["Placement","EDA"],"paperUrl":"https://arxiv.org/abs/2503.11674"}],"acceptanceRates":[],"keywordTrends":[]}