{"id":"sigir","slug":"sigir","nameEn":"ACM SIGIR Conference on Research and Development in Information Retrieval","nameKr":null,"acronym":"SIGIR","field":"AI/ML","subField":"Information Retrieval","dblpKey":"conf/sigir","websiteUrl":"https://sigir.org","description":null,"descriptionEn":"SIGIR (ACM SIGIR Conference on Research and Development in Information Retrieval). Paper deadline: 2026-01-22. 2026-07-20, Melbourne, Australia. BK21 4, KIISE 최우수, POSTECH 최우수, SNU 인정, CORE A*, CCF A, CSRankings Included, KAIST 최우수. 6 best paper awards.","descriptionKo":"SIGIR (ACM SIGIR Conference on Research and Development in Information Retrieval). 논문 마감: 2026-01-22. 2026-07-20, Melbourne, Australia. BK21 4, KIISE 최우수, POSTECH 최우수, SNU 인정, CORE A*, CCF A, CSRankings Included, KAIST 최우수. Best Paper 6편.","nextDeadline":"2026-01-22T23:59:00Z","daysUntilDeadline":-82,"deadlineTimezone":"AoE","venue":"Melbourne, Australia","conferenceStart":"2026-07-20","conferenceEnd":"2026-07-24","institutionRatings":[{"institution":"BK21","tier":"4"},{"institution":"KIISE","tier":"최우수"},{"institution":"POSTECH","tier":"최우수"},{"institution":"SNU","tier":"인정"},{"institution":"CORE","tier":"A*"},{"institution":"CCF","tier":"A"},{"institution":"CSRankings","tier":"Included"},{"institution":"KAIST","tier":"최우수"}],"deadlines":[{"year":2026,"cycle":"main","abstractDeadline":"2026-01-15T23:59:00Z","paperDeadline":"2026-01-22T23:59:00Z","notificationDate":"2026-03-20T00:00:00Z","conferenceStart":"2026-07-20","conferenceEnd":"2026-07-24","venue":"Melbourne, Australia","timezone":"AoE"}],"bestPapers":[{"year":2021,"paperTitle":"Computationally Efficient Optimization of Plackett-Luce Ranking Models for Relevance and Fairness","authors":"Harrie Oosterhuis","awardType":"best_paper","tags":["ranking","fairness","information retrieval","optimization"],"paperUrl":"http://arxiv.org/abs/2105.00855v2"},{"year":2022,"paperTitle":"Reduce, Reuse, Recycle: Green Information Retrieval Research","authors":"Scells, Zhuang, Zuccon","awardType":"honorable_mention","tags":["IR","Sustainability"],"paperUrl":"https://doi.org/10.1145/3477495.3531766"},{"year":2023,"paperTitle":"The Information Retrieval Experiment Platform","authors":"Fröbe et al.","awardType":"best_paper","tags":["IR","Platform"],"paperUrl":"http://arxiv.org/abs/2305.18932v1"},{"year":2025,"paperTitle":"WARP: An Efficient Engine for Multi-Vector Retrieval","authors":["Jan Luca Scheerer","Matei Zaharia","Christopher Potts","Gustavo Alonso","Omar Khattab"],"awardType":"best_paper","tags":["information retrieval","vector search","efficiency"],"paperUrl":"http://arxiv.org/abs/2501.17788v3"},{"year":2022,"paperTitle":"A Non-Factoid Question-Answering Taxonomy","authors":"Valeriia Bolotova, Vladislav Blinov, Falk Scholer, Bruce Croft, Mark Sanderson","awardType":"best_paper","tags":[],"paperUrl":"https://doi.org/10.1145/3477495.3531926"},{"year":2020,"paperTitle":"Controlling Fairness and Bias in Dynamic Learning-to-rank","authors":"Marco Morik, Ashudeep Singh, Jessica Hong, Thorsten Joachims","awardType":"best_paper","tags":["Fairness","Bias"],"paperUrl":"https://arxiv.org/abs/2005.14713"}],"acceptanceRates":[],"keywordTrends":[]}